noawclg/__init__.py
noawclg/api.py
noawclg/main.py
noawclg/plot.py
noawclg-0.0.8.dist-info/LICENSE
noawclg-0.0.8.dist-info/METADATA
noawclg-0.0.8.dist-info/WHEEL
noawclg-0.0.8.dist-info/top_level.txt
noawclg-0.0.8.dist-info/RECORD
