Metadata-Version: 2.1
Name: noawclg
Version: 0.0.8
Summary: Library for getting dataset from noaa site
Home-page: https://github.com/reinanbr/noawclg
Author: Reinan Br
Author-email: slimchatuba@gmail.com
License: GPLv3
Keywords: climate weather noaa
License-File: LICENSE
Requires-Dist: xarray
Requires-Dist: netCDF4
Requires-Dist: matplotlib
Requires-Dist: geopy
Requires-Dist: openpyxl
